{"rows":[{"kind":"view","event":"neighborhood","slug":"neighborhood-5.5","anon_id":"911c9a1e-b249-48ea-a322-bc0e45faf459","source":"seed","created_at":1753186686264},{"kind":"view","event":"neighborhood","slug":"neighborhood-3.5","anon_id":"911c9a1e-b249-48ea-a322-bc0e45faf459","source":"seed","created_at":1753186686268},{"kind":"view","event":"neighborhood","slug":"neighborhood-0.5","anon_id":"911c9a1e-b249-48ea-a322-bc0e45faf459","source":"seed","created_at":1753186686274},{"kind":"view","event":"neighborhood","slug":"neighborhood-23.5","anon_id":"911c9a1e-b249-48ea-a322-bc0e45faf459","source":"seed","created_at":1753558188132},{"kind":"view","event":"neighborhood","slug":"neighborhood-22.5","anon_id":"911c9a1e-b249-48ea-a322-bc0e45faf459","source":"seed","created_at":1753558188132},{"kind":"view","event":"neighborhood","slug":"neighborhood-21.5","anon_id":"911c9a1e-b249-48ea-a322-bc0e45faf459","source":"seed","created_at":1753558188132},{"kind":"view","event":"neighborhood","slug":"neighborhood-20.5","anon_id":"911c9a1e-b249-48ea-a322-bc0e45faf459","source":"seed","created_at":1753558188132},{"kind":"view","event":"neighborhood","slug":"neighborhood-19.5","anon_id":"911c9a1e-b249-48ea-a322-bc0e45faf459","source":"seed","created_at":1753558188132},{"kind":"view","event":"neighborhood","slug":"neighborhood-17.5","anon_id":"911c9a1e-b249-48ea-a322-bc0e45faf459","source":"seed","created_at":1753558188132},{"kind":"view","event":"neighborhood","slug":"neighborhood-18.5","anon_id":"911c9a1e-b249-48ea-a322-bc0e45faf459","source":"seed","created_at":1753558188137},{"kind":"view","event":"neighborhood","slug":"neighborhood-16.5","anon_id":"911c9a1e-b249-48ea-a322-bc0e45faf459","source":"seed","created_at":1753558188137},{"kind":"view","event":"neighborhood","slug":"neighborhood-15.5","anon_id":"911c9a1e-b249-48ea-a322-bc0e45faf459","source":"seed","created_at":1753558188140},{"kind":"view","event":"neighborhood","slug":"neighborhood-14.5","anon_id":"911c9a1e-b249-48ea-a322-bc0e45faf459","source":"seed","created_at":1753558188140},{"kind":"view","event":"neighborhood","slug":"neighborhood-13.5","anon_id":"911c9a1e-b249-48ea-a322-bc0e45faf459","source":"seed","created_at":1753558188144},{"kind":"view","event":"neighborhood","slug":"neighborhood-12.5","anon_id":"911c9a1e-b249-48ea-a322-bc0e45faf459","source":"seed","created_at":1753558188144},{"kind":"view","event":"neighborhood","slug":"neighborhood-11.5","anon_id":"911c9a1e-b249-48ea-a322-bc0e45faf459","source":"seed","created_at":1753558188148},{"kind":"view","event":"neighborhood","slug":"neighborhood-10.5","anon_id":"911c9a1e-b249-48ea-a322-bc0e45faf459","source":"seed","created_at":1753558188148},{"kind":"view","event":"neighborhood","slug":"neighborhood-9.5","anon_id":"911c9a1e-b249-48ea-a322-bc0e45faf459","source":"seed","created_at":1753558188151},{"kind":"view","event":"neighborhood","slug":"neighborhood-8.5","anon_id":"911c9a1e-b249-48ea-a322-bc0e45faf459","source":"seed","created_at":1753558188152},{"kind":"view","event":"neighborhood","slug":"neighborhood-7.5","anon_id":"911c9a1e-b249-48ea-a322-bc0e45faf459","source":"seed","created_at":1753558188155},{"kind":"view","event":"neighborhood","slug":"neighborhood-6.5","anon_id":"911c9a1e-b249-48ea-a322-bc0e45faf459","source":"seed","created_at":1753558188155},{"kind":"view","event":"neighborhood","slug":"neighborhood-5.5","anon_id":"911c9a1e-b249-48ea-a322-bc0e45faf459","source":"seed","created_at":1753558188158},{"kind":"view","event":"neighborhood","slug":"neighborhood-4.5","anon_id":"911c9a1e-b249-48ea-a322-bc0e45faf459","source":"seed","created_at":1753558188160},{"kind":"view","event":"neighborhood","slug":"neighborhood-3.5","anon_id":"911c9a1e-b249-48ea-a322-bc0e45faf459","source":"seed","created_at":1753558188161},{"kind":"view","event":"neighborhood","slug":"neighborhood-2.5","anon_id":"911c9a1e-b249-48ea-a322-bc0e45faf459","source":"seed","created_at":1753558188164},{"kind":"view","event":"neighborhood","slug":"neighborhood-1.5","anon_id":"911c9a1e-b249-48ea-a322-bc0e45faf459","source":"seed","created_at":1753558188164},{"kind":"view","event":"neighborhood","slug":"neighborhood-0.5","anon_id":"911c9a1e-b249-48ea-a322-bc0e45faf459","source":"seed","created_at":1753558188169},{"kind":"view","event":"neighborhood","slug":"neighborhood-23.5","anon_id":"add8113d-155d-4231-bc20-dbbac3eab814","source":"open","created_at":1753558190550},{"kind":"view","event":"neighborhood","slug":"neighborhood-23.5","anon_id":"add8113d-155d-4231-bc20-dbbac3eab814","source":"open","created_at":1753558195463},{"kind":"view","event":"neighborhood","slug":"neighborhood-22.5","anon_id":"add8113d-155d-4231-bc20-dbbac3eab814","source":"open","created_at":1753558197703},{"kind":"view","event":"neighborhood","slug":"neighborhood-23.5","anon_id":"add8113d-155d-4231-bc20-dbbac3eab814","source":"open","created_at":1753558470628},{"kind":"view","event":"neighborhood","slug":"neighborhood-22.5","anon_id":"add8113d-155d-4231-bc20-dbbac3eab814","source":"open","created_at":1753558496884},{"kind":"view","event":"neighborhood","slug":"neighborhood-16.5","anon_id":"add8113d-155d-4231-bc20-dbbac3eab814","source":"open","created_at":1753558514015},{"kind":"view","event":"neighborhood","slug":"neighborhood-13.5","anon_id":"add8113d-155d-4231-bc20-dbbac3eab814","source":"open","created_at":1753558527976},{"kind":"view","event":"neighborhood","slug":"neighborhood-11.5","anon_id":"add8113d-155d-4231-bc20-dbbac3eab814","source":"open","created_at":1753558575740},{"kind":"view","event":"neighborhood","slug":"neighborhood-12.5","anon_id":"add8113d-155d-4231-bc20-dbbac3eab814","source":"open","created_at":1753558576693},{"kind":"view","event":"neighborhood","slug":"neighborhood-13.5","anon_id":"add8113d-155d-4231-bc20-dbbac3eab814","source":"open","created_at":1753558578560},{"kind":"view","event":"neighborhood","slug":"neighborhood-14.5","anon_id":"add8113d-155d-4231-bc20-dbbac3eab814","source":"open","created_at":1753558579497},{"kind":"view","event":"neighborhood","slug":"neighborhood-15.5","anon_id":"add8113d-155d-4231-bc20-dbbac3eab814","source":"open","created_at":1753558582466},{"kind":"view","event":"neighborhood","slug":"neighborhood-16.5","anon_id":"add8113d-155d-4231-bc20-dbbac3eab814","source":"open","created_at":1753558585819},{"kind":"view","event":"neighborhood","slug":"neighborhood-23.5","anon_id":"add8113d-155d-4231-bc20-dbbac3eab814","source":"open","created_at":1753558701387},{"kind":"view","event":"neighborhood","slug":"neighborhood-23.5","anon_id":"add8113d-155d-4231-bc20-dbbac3eab814","source":"open","created_at":1753558727944},{"kind":"view","event":"neighborhood","slug":"neighborhood-21.5","anon_id":"add8113d-155d-4231-bc20-dbbac3eab814","source":"open","created_at":1753558760038},{"kind":"view","event":"neighborhood","slug":"neighborhood-21.5","anon_id":"add8113d-155d-4231-bc20-dbbac3eab814","source":"open","created_at":1753558782192},{"kind":"view","event":"neighborhood","slug":"neighborhood-21.5","anon_id":"add8113d-155d-4231-bc20-dbbac3eab814","source":"open","created_at":1753558819993},{"kind":"view","event":"neighborhood","slug":"neighborhood-22.5","anon_id":"add8113d-155d-4231-bc20-dbbac3eab814","source":"open","created_at":1753558830683},{"kind":"view","event":"neighborhood","slug":"neighborhood-21.5","anon_id":"add8113d-155d-4231-bc20-dbbac3eab814","source":"open","created_at":1753559086775},{"kind":"view","event":"neighborhood","slug":"neighborhood-21.5","anon_id":"add8113d-155d-4231-bc20-dbbac3eab814","source":"open","created_at":1753559098225},{"kind":"view","event":"neighborhood","slug":"neighborhood-23.5","anon_id":"add8113d-155d-4231-bc20-dbbac3eab814","source":"open","created_at":1753559399560},{"kind":"view","event":"neighborhood","slug":"neighborhood-22.5","anon_id":"add8113d-155d-4231-bc20-dbbac3eab814","source":"open","created_at":1753559399562},{"kind":"view","event":"neighborhood","slug":"neighborhood-21.5","anon_id":"add8113d-155d-4231-bc20-dbbac3eab814","source":"open","created_at":1753559399562},{"kind":"view","event":"neighborhood","slug":"neighborhood-20.5","anon_id":"add8113d-155d-4231-bc20-dbbac3eab814","source":"open","created_at":1753559399564},{"kind":"view","event":"neighborhood","slug":"neighborhood-19.5","anon_id":"add8113d-155d-4231-bc20-dbbac3eab814","source":"open","created_at":1753559399565},{"kind":"view","event":"neighborhood","slug":"neighborhood-17.5","anon_id":"add8113d-155d-4231-bc20-dbbac3eab814","source":"open","created_at":1753559399565},{"kind":"view","event":"neighborhood","slug":"neighborhood-18.5","anon_id":"add8113d-155d-4231-bc20-dbbac3eab814","source":"open","created_at":1753559399569},{"kind":"view","event":"neighborhood","slug":"neighborhood-16.5","anon_id":"add8113d-155d-4231-bc20-dbbac3eab814","source":"open","created_at":1753559399569},{"kind":"view","event":"neighborhood","slug":"neighborhood-15.5","anon_id":"add8113d-155d-4231-bc20-dbbac3eab814","source":"open","created_at":1753559399570},{"kind":"view","event":"neighborhood","slug":"neighborhood-14.5","anon_id":"add8113d-155d-4231-bc20-dbbac3eab814","source":"open","created_at":1753559399572},{"kind":"view","event":"neighborhood","slug":"neighborhood-13.5","anon_id":"add8113d-155d-4231-bc20-dbbac3eab814","source":"open","created_at":1753559399573},{"kind":"view","event":"neighborhood","slug":"neighborhood-12.5","anon_id":"add8113d-155d-4231-bc20-dbbac3eab814","source":"open","created_at":1753559399573},{"kind":"view","event":"neighborhood","slug":"neighborhood-11.5","anon_id":"add8113d-155d-4231-bc20-dbbac3eab814","source":"open","created_at":1753559399573},{"kind":"view","event":"neighborhood","slug":"neighborhood-10.5","anon_id":"add8113d-155d-4231-bc20-dbbac3eab814","source":"open","created_at":1753559399573},{"kind":"view","event":"neighborhood","slug":"neighborhood-9.5","anon_id":"add8113d-155d-4231-bc20-dbbac3eab814","source":"open","created_at":1753559399575},{"kind":"view","event":"neighborhood","slug":"neighborhood-8.5","anon_id":"add8113d-155d-4231-bc20-dbbac3eab814","source":"open","created_at":1753559399576},{"kind":"view","event":"neighborhood","slug":"neighborhood-7.5","anon_id":"add8113d-155d-4231-bc20-dbbac3eab814","source":"open","created_at":1753559399577},{"kind":"view","event":"neighborhood","slug":"neighborhood-6.5","anon_id":"add8113d-155d-4231-bc20-dbbac3eab814","source":"open","created_at":1753559399579},{"kind":"view","event":"neighborhood","slug":"neighborhood-5.5","anon_id":"add8113d-155d-4231-bc20-dbbac3eab814","source":"open","created_at":1753559399580},{"kind":"view","event":"neighborhood","slug":"neighborhood-4.5","anon_id":"add8113d-155d-4231-bc20-dbbac3eab814","source":"open","created_at":1753559399581},{"kind":"view","event":"neighborhood","slug":"neighborhood-3.5","anon_id":"add8113d-155d-4231-bc20-dbbac3eab814","source":"open","created_at":1753559399582},{"kind":"view","event":"neighborhood","slug":"neighborhood-2.5","anon_id":"add8113d-155d-4231-bc20-dbbac3eab814","source":"open","created_at":1753559399584},{"kind":"view","event":"neighborhood","slug":"neighborhood-1.5","anon_id":"add8113d-155d-4231-bc20-dbbac3eab814","source":"open","created_at":1753559399585},{"kind":"view","event":"neighborhood","slug":"neighborhood-0.5","anon_id":"add8113d-155d-4231-bc20-dbbac3eab814","source":"open","created_at":1753559399586}]}